[{"s": "blok-besperebojnogo-pitaniya-eto", "t": "Блок бесперебойного питания (ИБП): что это, как выбрать и подключить", "i": "🔋", "c": "stabilizatory-i-ibp"}, {"s": "blok-rezervnogo-pitaniya-eto", "t": "Блок резервного питания (ИБП): виды, выбор и подключение", "i": "🔋", "c": "stabilizatory-i-ibp"}, {"s": "blok-pitaniya-s-akb", "t": "Блок питания с АКБ: выбор, подключение и безопасность (2026)", "i": "🔋", "c": "stabilizatory-i-ibp"}, {"s": "blok-rezervirovaniya-pitaniya", "t": "Блок резервирования питания: как выбрать и подключить правильно", "i": "🔋", "c": "stabilizatory-i-ibp"}, {"s": "blok-zazhimov-dlya-soedineniya-zhil-provodov", "t": "Блоки зажимов для проводов: виды, монтаж и выбор (2026)", "i": "🔌", "c": "rozetki-i-vyklyuchateli"}, {"s": "blok-avtonomnogo-pitaniya", "t": "Блок автономного питания: выбор, подключение и безопасность в 2026 году", "i": "🔋", "c": "stabilizatory-i-ibp"}, {"s": "blink-led-tester-instruktsiya-na-russkom", "t": "Blink LED-тестер: инструкция на русском с схемами и советами", "i": "🔍", "c": "poisk-neispravnostej"}, {"s": "blok-besperebojnogo-pitaniya-dlya-kompyutera-kakoj-vybrat", "t": "Как выбрать ИБП для компьютера: 7 критериев и рейтинг 2026", "i": "🔋", "c": "stabilizatory-i-ibp"}, {"s": "blok-pitaniya-dlya-akkumulyatora", "t": "Блок питания для аккумулятора: выбор, подключение, безопасность", "i": "🔋", "c": "stabilizatory-i-ibp"}, {"s": "blok-rezervirovannogo-pitaniya", "t": "Блок резервированного питания: выбор, подключение и ошибки монтажа", "i": "🔋", "c": "stabilizatory-i-ibp"}, {"s": "blok-s-rozetkami-kak-nazyvaetsya", "t": "Блок розеток: как называется, виды и правила монтажа", "i": "🔌", "c": "rozetki-i-vyklyuchateli"}, {"s": "bluzhdayushchij-tok-v-sisteme-vodosnabzheniya", "t": "Блуждающий ток в водопроводе: причины, опасности и защита", "i": "🔍", "c": "poisk-neispravnostej"}, {"s": "blok-pitaniya-eto-akkumulyator", "t": "Блок питания и аккумулятор: в чем разница и можно ли заменить?", "i": "🔋", "c": "stabilizatory-i-ibp"}, {"s": "blok-pitaniya-iz-ibp", "t": "Как сделать блок питания из ИБП: пошаговая инструкция и схемы", "i": "🔋", "c": "stabilizatory-i-ibp"}, {"s": "blok-pitaniya-s-akkumulyatorom", "t": "Блок питания с аккумулятором: как выбрать и подключить правильно", "i": "🔋", "c": "stabilizatory-i-ibp"}, {"s": "blok-dlya-elektrichestva", "t": "Блок для электричества: виды, выбор и монтаж электрощитка", "i": "🛡️", "c": "elektroshchit-i-avtomaty"}, {"s": "blok-pitaniya-s-besperebojnikom", "t": "Блок питания с бесперебойником: виды, схемы и выбор", "i": "🔋", "c": "stabilizatory-i-ibp"}, {"s": "bloki-pitaniya-s-rezervirovaniem", "t": "Блоки питания с резервированием: выбор, схемы и монтаж", "i": "🔋", "c": "stabilizatory-i-ibp"}, {"s": "blok-istochnika-rezervirovannogo-pitaniya", "t": "Блок источника резервированного питания: устройство, типы и монтаж", "i": "🔋", "c": "stabilizatory-i-ibp"}, {"s": "blok-besperebojnogo-pitaniya-prednaznachen-dlya", "t": "Блок бесперебойного питания: для чего нужен, устройство и выбор", "i": "🔋", "c": "stabilizatory-i-ibp"}, {"s": "bluzhdayushchie-toki-v-vodoprovode", "t": "Блуждающие токи в водопроводе: причины и защита", "i": "📁", "c": null}, {"s": "blok-pitaniya-iz-besperebojnika", "t": "Блок питания из ИБП: как сделать своими руками", "i": "🔋", "c": "stabilizatory-i-ibp"}]