[{"s": "gde-raspolozhit-rozetku-dlya-varochnoj-paneli", "t": "Где установить розетку для варочной панели: 5 правил + схема", "i": "🍳", "c": "elektrika-na-kukhne"}, {"s": "gde-raspolozhit-rozetku-dlya-konditsionera", "t": "Где установить розетку для кондиционера: 7 правил + схема подключения", "i": "🔌", "c": "rozetki-i-vyklyuchateli"}, {"s": "gde-raspolozhit-elektroshchit-v-chastnom-dome", "t": "Где установить электрощит в частном доме: 5 ключевых правил монтажа", "i": "🛡️", "c": "elektroshchit-i-avtomaty"}, {"s": "gde-raspolozhit-rozetku-dlya-posudomoechnoj-mashiny", "t": "Где поставить розетку для посудомоечной машины: 5 правил + схема", "i": "🍳", "c": "elektrika-na-kukhne"}, {"s": "gde-raspolozhit-rozetku-dlya-vytyazhki-na-kukhne", "t": "Где установить розетку для вытяжки на кухне: 5 правил + схема", "i": "🍳", "c": "elektrika-na-kukhne"}, {"s": "gde-raspolozhit-rozetki-za-televizorom-na-stene", "t": "Где расположить розетки за телевизором на стене: схема и ошибки", "i": "🔌", "c": "rozetki-i-vyklyuchateli"}, {"s": "gde-raspolozhit-rozetku-dlya-dukhovogo-shkafa", "t": "Где установить розетку для духового шкафа: 5 правил + схема подключения", "i": "🍳", "c": "elektrika-na-kukhne"}, {"s": "gde-raspolozhit-shchitok-v-chastnom-dome", "t": "Где установить щиток в частном доме: 7 лучших мест + нормы ПУЭ", "i": "🛡️", "c": "elektroshchit-i-avtomaty"}, {"s": "gde-razmestit-rozetku-dlya-vstroennogo-kholodilnika", "t": "Где разместить розетку для встроенного холодильника: 5 правил и схемы", "i": "🍳", "c": "elektrika-na-kukhne"}, {"s": "gde-raspolozhit-rozetku-dlya-kholodilnika", "t": "Где расположить розетку для холодильника: 7 правил от электрика", "i": "🍳", "c": "elektrika-na-kukhne"}, {"s": "gde-raspolozhit-rozetku-dlya-vstroennogo-kholodilnika", "t": "Где поставить розетку для встроенного холодильника: 5 ошибок и правила монтажа", "i": "🍳", "c": "elektrika-na-kukhne"}, {"s": "gde-raspolozhit-elektroshchit-v-kvartire", "t": "Где установить электрощит в квартире: нормы, схемы и ошибки 2026", "i": "🛡️", "c": "elektroshchit-i-avtomaty"}, {"s": "gde-raspolagat-rozetku-dlya-dukhovogo-shkafa", "t": "Где установить розетку для духового шкафа: правила и ошибки", "i": "🍳", "c": "elektrika-na-kukhne"}, {"s": "gde-razmestit-rozetku-dlya-dukhovogo-shkafa", "t": "Где разместить розетку для духового шкафа: нормы и схемы", "i": "🍳", "c": "elektrika-na-kukhne"}, {"s": "gde-raspolozhit-rozetki-na-kukhne-dlya-tekhniki-vstraivaemoj", "t": "Где расположить розетки на кухне для встраиваемой техники", "i": "🍳", "c": "elektrika-na-kukhne"}, {"s": "gde-raspolozhit-rozetku-dlya-stiralnoj-mashiny", "t": "Где расположить розетку для стиральной машины: нормы и схемы", "i": "🍳", "c": "elektrika-na-kukhne"}, {"s": "gde-rozetka-dlya-vytyazhki-na-kukhne-delat", "t": "Где делать розетку для вытяжки на кухне: схема и высота", "i": "🍳", "c": "elektrika-na-kukhne"}]