[{"s": "krasivaya-sborka-elektroshchita", "t": "Красивая сборка электрощита: 10 шагов к идеальному монтажу", "i": "🛡️", "c": "elektroshchit-i-avtomaty"}, {"s": "kreplenie-provoda-k-stene-derevyannogo-doma", "t": "Крепление провода к стене деревянного дома: безопасность и способы монтажа", "i": "🏡", "c": "chastnyj-dom-i-dacha"}, {"s": "kreplenie-retro-kabelya", "t": "Крепление ретро кабеля: способы, инструменты и ошибки монтажа", "i": "🧵", "c": "provodka-i-kabeli"}, {"s": "krimper-chto-eto-takoe-prostymi-slovami", "t": "Кримпер — что это такое простыми словами: виды и применение", "i": "🔧", "c": "instrumenty-i-zamery"}, {"s": "krimper-dlya-obzhima-nakonechnikov-i-zachistki-provodov", "t": "Кримпер для обжима наконечников: как выбрать и пользоваться (2026)", "i": "🔧", "c": "instrumenty-i-zamery"}, {"s": "kreplenie-kabel-kanala-k-gipsokartonu", "t": "Как закрепить кабель-канал на гипсокартоне: 5 надежных способов", "i": "🧵", "c": "provodka-i-kabeli"}, {"s": "kreplenie-sip-kabelya-k-domu-derevyannomu", "t": "Крепление СИП кабеля к деревянному дому: правила и ошибки 2026", "i": "🏡", "c": "chastnyj-dom-i-dacha"}, {"s": "kreplenie-vvg-k-derevyannoj-stene", "t": "Как крепить кабель ВВГ к деревянной стене: 5 безопасных способов", "i": "🧵", "c": "provodka-i-kabeli"}, {"s": "kreplenie-rozetok-k-stene", "t": "Как правильно закрепить розетку в стене: 5 проверенных способов", "i": "🔌", "c": "rozetki-i-vyklyuchateli"}, {"s": "kran-bet-tokom-v-chastnom-dome", "t": "Кран бьет током в частном доме: причины и что делать в 2026 году", "i": "🔍", "c": "poisk-neispravnostej"}, {"s": "kran-betsya-tokom-v-kvartire", "t": "Кран бьёт током в квартире: причины и что делать — инструкция 2026", "i": "🔍", "c": "poisk-neispravnostej"}, {"s": "kreplenie-provodov-na-stolbe", "t": "Крепление проводов на столбе: нормы, способы и ошибки монтажа", "i": "🧵", "c": "provodka-i-kabeli"}, {"s": "krimper-dlya-obzhima-avtoklemm-kakoj-luchshe", "t": "Кримпер для автоклемм: какой выбрать в 2026? ТОП-5 моделей", "i": "🔧", "c": "instrumenty-i-zamery"}, {"s": "krimper-eto-instrument", "t": "Кримпер: что это за инструмент и как им пользоваться в электромонтаже", "i": "🔧", "c": "instrumenty-i-zamery"}, {"s": "krivye-ploskogubtsy-nazvanie", "t": "Кривые плоскогубцы: название, виды и применение в электромонтаже", "i": "🔧", "c": "instrumenty-i-zamery"}, {"s": "kran-bet-tokom", "t": "Кран бьёт током: причины и что делать в 2026 году", "i": "⚠️", "c": "bezopasnost-i-zazemlenie"}, {"s": "krimper-kak-rabotaet", "t": "Кримпер для обжима кабелей: как работает и как выбрать", "i": "🔧", "c": "instrumenty-i-zamery"}, {"s": "kran-bet-tokom-prichina", "t": "Кран бьет током: 7 причин и что делать в 2026 году", "i": "⚠️", "c": "bezopasnost-i-zazemlenie"}, {"s": "krasivaya-sborka-shchita", "t": "Красивая сборка щита: 7 шагов к эстетике и безопасности", "i": "🛡️", "c": "elektroshchit-i-avtomaty"}, {"s": "kratnost-avtomatov-a-v-s-d", "t": "Кратность автоматов A, B, C, D: таблица, расчет и выбор для дома", "i": "🛡️", "c": "elektroshchit-i-avtomaty"}, {"s": "kreplenie-vyklyuchatelya-v-podrozetnik", "t": "Как закрепить выключатель в подрозетнике: инструкция 2026", "i": "🔌", "c": "rozetki-i-vyklyuchateli"}, {"s": "kran-na-kukhne-bet-tokom", "t": "Кран на кухне бьёт током: причины и что делать в 2026 году", "i": "🔍", "c": "poisk-neispravnostej"}, {"s": "kreplenie-provoda-sip-na-opore", "t": "Крепление провода СИП на опоре: нормы, схемы, ошибки монтажа", "i": "🧵", "c": "provodka-i-kabeli"}, {"s": "kreplenie-gofry-k-polu", "t": "Крепление гофры к полу: 5 способов + ошибки монтажа (2026)", "i": "🧵", "c": "provodka-i-kabeli"}, {"s": "kreplenie-retro-provoda", "t": "Крепление ретро-провода: 5 способов + инструкции с фото", "i": "🧵", "c": "provodka-i-kabeli"}, {"s": "krimper-dlya-chego", "t": "Кримпер: для чего нужен, виды и как выбрать инструмент", "i": "🔧", "c": "instrumenty-i-zamery"}, {"s": "krimper-dlya-obzhima-provodov-kak-polzovatsya", "t": "Кримпер для обжима проводов: как пользоваться правильно", "i": "🔧", "c": "instrumenty-i-zamery"}, {"s": "kreplenie-kabel-kanala-k-stene-bez-sverleniya", "t": "Как закрепить кабель-канал без сверления: 7 проверенных способов", "i": "🧵", "c": "provodka-i-kabeli"}, {"s": "krimper-i-stripper-otlichiya", "t": "Кримпер и стриппер: ключевые отличия и когда что использовать", "i": "🔧", "c": "instrumenty-i-zamery"}, {"s": "krimper-eto-chto", "t": "Кримпер: что это такое и как выбрать для обжима проводов", "i": "🔧", "c": "instrumenty-i-zamery"}, {"s": "krasnyj-provod-na-plyus-ili-na-minus", "t": "Красный провод — плюс или минус? Разбираемся в цветах проводов", "i": "🧵", "c": "provodka-i-kabeli"}, {"s": "krimper-svoimi-rukami", "t": "Кримпер своими руками: 5 проверенных способов изготовления", "i": "🔧", "c": "instrumenty-i-zamery"}, {"s": "krepit-kabel-kanal", "t": "Как крепить кабель-канал: 5 способов монтажа + ошибки новичков", "i": "🧵", "c": "provodka-i-kabeli"}, {"s": "kreplenie-kabelya-k-derevyannoj-stene", "t": "Крепление кабеля к деревянной стене: 7 способов + инструкции 2026", "i": "🧵", "c": "provodka-i-kabeli"}, {"s": "kreplenie-retro-provoda-na-izolyatory", "t": "Крепление ретро-провода на изоляторы: пошаговая инструкция 2026", "i": "🧵", "c": "provodka-i-kabeli"}, {"s": "krasnaya-gofra-dlya-kabelya-naznachenie", "t": "Красная гофра для кабеля: назначение, виды и правила монтажа", "i": "🧵", "c": "provodka-i-kabeli"}, {"s": "kreplenie-provodki-k-stene-pod-shtukaturku", "t": "Крепление проводки под штукатурку: способы, материалы, ошибки (2026)", "i": "🧵", "c": "provodka-i-kabeli"}, {"s": "kreplenie-rozetki-v-stene", "t": "Как закрепить розетку в стене: 5 проверенных способов (2026)", "i": "🔌", "c": "rozetki-i-vyklyuchateli"}, {"s": "krepkaya-skrutka-provodov", "t": "Как сделать крепкую скрутку проводов: 5 методов + ошибки", "i": "🧵", "c": "provodka-i-kabeli"}, {"s": "kruglye-ploskogubtsy-kak-nazyvayutsya", "t": "Круглые плоскогубцы: как называются и где применяются", "i": "🔧", "c": "instrumenty-i-zamery"}, {"s": "krysha-doma-bet-tokom", "t": "Крыша дома бьёт током: причины и как устранить опасность", "i": "🏡", "c": "chastnyj-dom-i-dacha"}, {"s": "kreplenie-elektroprovodki-k-stene-iz-kirpicha", "t": "Как закрепить электропроводку на кирпичной стене: 5 способов + схемы", "i": "🧵", "c": "provodka-i-kabeli"}, {"s": "krivaya-otklyucheniya-avtomata", "t": "Кривая отключения автомата: как выбрать и настроить правильно", "i": "🛡️", "c": "elektroshchit-i-avtomaty"}, {"s": "krasivo-sobrannyj-elektroshchit", "t": "Красивый электрощит: 10 правил сборки и дизайна 2026", "i": "🛡️", "c": "elektroshchit-i-avtomaty"}, {"s": "krimper-dlya-obzhima-avtoklemm-kak-polzovatsya", "t": "Кримпер для автоклемм: как пользоваться правильно (инструкция 2026)", "i": "🔧", "c": "instrumenty-i-zamery"}, {"s": "kreplenie-provoda-k-derevyannoj-stene", "t": "Как закрепить провод на деревянной стене: 5 безопасных способов", "i": "🧵", "c": "provodka-i-kabeli"}, {"s": "kreplenie-sip-k-opore-lep", "t": "Крепление СИП к опоре ЛЭП: нормы, схемы и ошибки монтажа", "i": "🧵", "c": "provodka-i-kabeli"}, {"s": "krimper-dlya-chego-nuzhen", "t": "Кримпер: для чего нужен и как выбрать инструмент для обжима", "i": "🔧", "c": "instrumenty-i-zamery"}, {"s": "krimper-dlya-obzhima-uglovykh-klemm", "t": "Кримпер для обжима угловых клемм: выбор, применение, ошибки", "i": "🔧", "c": "instrumenty-i-zamery"}, {"s": "kreplenie-retro-provodki", "t": "Крепление ретро-проводки: 5 способов + схемы монтажа 2026", "i": "🧵", "c": "provodka-i-kabeli"}, {"s": "krimper-dlya-obzhima-klemm-i-nakonechnikov", "t": "Кримпер для обжима клемм: как выбрать и пользоваться правильно", "i": "🔧", "c": "instrumenty-i-zamery"}, {"s": "kran-betsya-tokom", "t": "Кран бьется током: причины, поиск пробоя и устранение", "i": "⚠️", "c": "bezopasnost-i-zazemlenie"}, {"s": "kreplenie-elektroprovodki-na-ulitse", "t": "Крепление электропроводки на улице: нормы, материалы и монтаж", "i": "🧵", "c": "provodka-i-kabeli"}, {"s": "krepezh-dlya-provodov-mezhdu-soboj", "t": "Крепеж для проводов между собой: виды, выбор и монтаж", "i": "🧵", "c": "provodka-i-kabeli"}, {"s": "krab-dlya-soedineniya-provodov", "t": "Краб для соединения проводов: виды, монтаж и схемы", "i": "🧵", "c": "provodka-i-kabeli"}, {"s": "krimper-dlya-obzhima-koltsevykh-nakonechnikov", "t": "Кримпер для обжима кольцевых наконечников: выбор и применение", "i": "🔧", "c": "instrumenty-i-zamery"}, {"s": "kreplenie-provodov-k-stene-bez-sverleniya", "t": "Крепление проводов к стене без сверления: лучшие способы", "i": "🧵", "c": "provodka-i-kabeli"}, {"s": "krimper-dlya-obzhima-nakonechnikov-kak-polzovatsya", "t": "Кримпер для обжима наконечников: пошаговая инструкция", "i": "🔧", "c": "instrumenty-i-zamery"}, {"s": "kreplenie-rozetki-v-podrozetnik", "t": "Крепление розетки в подрозетник: пошаговая инструкция и ошибки", "i": "🔌", "c": "rozetki-i-vyklyuchateli"}, {"s": "krimper-dlya-provodov-pod-obzhim", "t": "Кримпер для проводов: виды, выбор и инструкция по обжиму", "i": "🔧", "c": "instrumenty-i-zamery"}, {"s": "krimper-kak-polzovatsya", "t": "Как пользоваться кримпером: полная инструкция для электрика", "i": "🔧", "c": "instrumenty-i-zamery"}, {"s": "krasnyj-na-akkumulyatore-plyus", "t": "Красный на аккумуляторе плюс: как определить полярность и не перепутать клеммы", "i": "⚠️", "c": "bezopasnost-i-zazemlenie"}, {"s": "krepezh-dlya-retro-provodki", "t": "Крепеж для ретро проводки: виды, монтаж и секреты фиксации", "i": "🧵", "c": "provodka-i-kabeli"}, {"s": "kreplenie-provodov-v-kabel-kanale", "t": "Крепление проводов в кабель-канале: пошаговая инструкция и нормы ПУЭ", "i": "🧵", "c": "provodka-i-kabeli"}, {"s": "krasnyj-shchup-multimetra-eto-plyus-ili-minus", "t": "Красный щуп мультиметра: плюс или минус? Полярность и обозначения", "i": "🔧", "c": "instrumenty-i-zamery"}, {"s": "krimper-kakoj-vybrat-dlya-doma", "t": "Кримпер для обжима витой пары: какой выбрать для дома?", "i": "🔧", "c": "instrumenty-i-zamery"}, {"s": "kriterii-vybora-avtomaticheskogo-vyklyuchatelya", "t": "Критерии выбора автоматического выключателя: ток, полюса, класс", "i": "🛡️", "c": "elektroshchit-i-avtomaty"}, {"s": "krimper-dlya-obzhima-nshvi", "t": "Кримпер для обжима НШВИ: выбор инструмента и инструкция", "i": "🔧", "c": "instrumenty-i-zamery"}, {"s": "krimper-dlya-obzhima-kak-polzovatsya", "t": "Как пользоваться кримпером: инструкция по обжиму", "i": "🔧", "c": "instrumenty-i-zamery"}, {"s": "kreplenie-provodki-k-potolku-bez-gofry", "t": "Крепление проводки к потолку без гофры: методы и нормы", "i": "🧵", "c": "provodka-i-kabeli"}]