[{"s": "negoryuchij-kabel-dlya-elektroprovodki-v-derevyannom-dome", "t": "Негорючий кабель для деревянного дома: виды, монтаж, нормы 2026", "i": "🧵", "c": "provodka-i-kabeli"}, {"s": "net-elektrichestva-v-kvartire-avtomaty-vklyucheny", "t": "Нет электричества в квартире, а автоматы включены: причины и решение", "i": "🔍", "c": "poisk-neispravnostej"}, {"s": "net-fazy-v-rozetke-v-chem-prichina", "t": "Нет фазы в розетке: 7 причин и как устранить неисправность", "i": "🔍", "c": "poisk-neispravnostej"}, {"s": "net-zazemleniya-v-dome-chem-opasno", "t": "Нет заземления в доме: чем опасно и как защититься", "i": "⚠️", "c": "bezopasnost-i-zazemlenie"}, {"s": "ne-derzhit-avtomat", "t": "Автомат не держит нагрузку: причины и что делать в 2026 году", "i": "🛡️", "c": "elektroshchit-i-avtomaty"}, {"s": "ne-rabotayut-rozetki-v-kvartire-a-svet-est-avtomat-vklyuchen-prichiny", "t": "Не работают розетки, а свет есть: причины и решения (автомат включен)", "i": "🔍", "c": "poisk-neispravnostej"}, {"s": "ne-rabotayut-rozetki-v-kvartire", "t": "Не работают розетки в квартире: причины и что делать самостоятельно", "i": "🔍", "c": "poisk-neispravnostej"}, {"s": "ne-rabotaet-rozetka-kak-pochinit", "t": "Не работает розетка: как починить самостоятельно (пошагово)", "i": "🔍", "c": "poisk-neispravnostej"}, {"s": "ne-zavoditsya-generator-benzinovyj-prichina", "t": "Бензогенератор не заводится: 10 причин и как починить самостоятельно", "i": "🔍", "c": "poisk-neispravnostej"}, {"s": "net-povoda-dlya-provoda", "t": "Нет повода для провода: когда электромонтаж не нужен и как сэкономить", "i": "🧵", "c": "provodka-i-kabeli"}, {"s": "net-zazemleniya-v-dome", "t": "Нет заземления в доме: опасности, решения и законные нормы 2026", "i": "⚠️", "c": "bezopasnost-i-zazemlenie"}, {"s": "ne-khvataet-rozetok-na-kukhne-chto-delat", "t": "Не хватает розеток на кухне: 7 способов решить проблему", "i": "🍳", "c": "elektrika-na-kukhne"}, {"s": "ne-rabotaet-rozetka-prichiny", "t": "Не работает розетка: 12 причин и способы устранения неисправности", "i": "🔍", "c": "poisk-neispravnostej"}, {"s": "ne-rabotayut-rozetki-v-komnate", "t": "Не работают розетки в комнате: причины и что делать в 2026 году", "i": "🔍", "c": "poisk-neispravnostej"}, {"s": "neotklyuchaemaya-gruppa-v-shchitke-skhema", "t": "Неотключаемая группа в щитке: схема, нормы и подключение", "i": "🛡️", "c": "elektroshchit-i-avtomaty"}, {"s": "ne-rabotaet-odna-rozetka-v-kvartire-prichiny", "t": "Не работает розетка в квартире: 7 причин и как устранить", "i": "🔍", "c": "poisk-neispravnostej"}, {"s": "neobkhodimyj-instrument-dlya-elektrika", "t": "Топ-15 инструментов электрика: что обязательно должно быть в сумке", "i": "🔧", "c": "instrumenty-i-zamery"}, {"s": "ne-vklyuchaetsya-avtomat-v-shchitke", "t": "Не включается автомат в щитке: причины и решения (2026)", "i": "🛡️", "c": "elektroshchit-i-avtomaty"}, {"s": "ne-vklyuchaetsya-difavtomat", "t": "Не включается дифавтомат: 7 причин и как устранить поломку", "i": "🛡️", "c": "elektroshchit-i-avtomaty"}, {"s": "neispravnosti-avtomata-elektricheskogo-priznaki", "t": "Признаки неисправности автомата в щитке: как распознать поломку", "i": "🛡️", "c": "elektroshchit-i-avtomaty"}, {"s": "net-zazemleniya-v-kvartire", "t": "Нет заземления в квартире: что делать и чем это опасно?", "i": "⚠️", "c": "bezopasnost-i-zazemlenie"}, {"s": "ne-rabotaet-rozetka-v-kvartire-chto-delat-prichiny", "t": "Не работает розетка в квартире: причины и что делать самостоятельно", "i": "🔍", "c": "poisk-neispravnostej"}, {"s": "ne-zapuskaetsya-generator-benzinovyj", "t": "Не запускается бензогенератор: причины и ремонт своими руками", "i": "🔍", "c": "poisk-neispravnostej"}, {"s": "ne-vklyuchaetsya-schetchik-elektroenergii", "t": "Счётчик электроэнергии не включается: причины и решения", "i": "🔍", "c": "poisk-neispravnostej"}, {"s": "neispravnost-avtomaticheskogo-vyklyuchatelya", "t": "Неисправности автоматического выключателя: как найти и устранить", "i": "🛡️", "c": "elektroshchit-i-avtomaty"}, {"s": "neobkhodimost-zashchitnogo-zazemleniya", "t": "Зачем нужно защитное заземление в доме: риски и нормы 2026", "i": "⚠️", "c": "bezopasnost-i-zazemlenie"}, {"s": "net-elektrichestva-v-dome", "t": "Нет электричества в доме: причины и что делать в 2026 году", "i": "🔍", "c": "poisk-neispravnostej"}, {"s": "ne-rabotayut-rozetki-doma", "t": "Не работают розетки в доме: причины и решение проблемы", "i": "🔍", "c": "poisk-neispravnostej"}, {"s": "ne-zavoditsya-benzinovyj-generator-v-chem-prichina", "t": "Не заводится бензогенератор: 10 причин и способы устранения", "i": "🔍", "c": "poisk-neispravnostej"}, {"s": "ne-zavoditsya-benzogenerator-prichiny-i-sposoby", "t": "Бензогенератор не заводится: 10 причин и как устранить", "i": "🔍", "c": "poisk-neispravnostej"}, {"s": "net-odnoj-fazy-iz-trekh-chto-delat", "t": "Нет одной фазы из трёх: причины и решения проблемы в 2026 году", "i": "🔍", "c": "poisk-neispravnostej"}, {"s": "ne-rabotaet-elektrichestvo-v-kvartire", "t": "Пропал свет в квартире: причины и что делать самостоятельно", "i": "🔍", "c": "poisk-neispravnostej"}, {"s": "ne-rabotayut-vse-rozetki-v-kvartire-a-svet-est", "t": "Не работают розетки, а свет есть: причины и решения (2026)", "i": "🔍", "c": "poisk-neispravnostej"}, {"s": "neispravnosti-avtomata-elektricheskogo", "t": "Неисправности автомата: 7 признаков поломки и способы ремонта", "i": "🛡️", "c": "elektroshchit-i-avtomaty"}, {"s": "ne-rabotaet-odna-faza-iz-trekh-v-chastnom-dome", "t": "Не работает одна фаза в доме: причины и решение (2026)", "i": "🔍", "c": "poisk-neispravnostej"}, {"s": "ne-rabotaet-rozetka-v-kvartire", "t": "Не работает розетка в квартире: причины и что делать", "i": "🔌", "c": "rozetki-i-vyklyuchateli"}, {"s": "ne-rabotaet-rozetka-prichina", "t": "Не работает розетка: 9 причин и как устранить поломку", "i": "🔍", "c": "poisk-neispravnostej"}, {"s": "ne-rabotaet-rozetka-v-kvartire-chto-delat", "t": "Не работает розетка в квартире: 7 причин и что делать", "i": "🔍", "c": "poisk-neispravnostej"}, {"s": "ne-rabotaet-rozetka-v-kvartire-prichiny", "t": "Не работает розетка в квартире: 7 причин и способы устранения", "i": "🔍", "c": "poisk-neispravnostej"}, {"s": "ne-derzhitsya-rozetka-v-betonnoj-stene-chto-sdelat", "t": "Розетка выпадает из бетона: 7 способов крепления + инструкции", "i": "🔌", "c": "rozetki-i-vyklyuchateli"}, {"s": "ne-rabotaet-multimetr", "t": "Не работает мультиметр: причины и способы ремонта", "i": "🔧", "c": "instrumenty-i-zamery"}, {"s": "net-odnoj-fazy", "t": "Нет одной фазы в розетке: причины и решения проблемы", "i": "🔍", "c": "poisk-neispravnostej"}, {"s": "ne-derzhit-avtomat-v-shchitke", "t": "Автомат в щитке не держит: причины и как устранить", "i": "🔍", "c": "poisk-neispravnostej"}, {"s": "neobkhodima-li-zamena-elementov-v-avtomaticheskom-vyklyuchatele-posle-ego-srabatyvaniya", "t": "Нужно ли менять автомат после срабатывания? Разбор 2026 года", "i": "🛡️", "c": "elektroshchit-i-avtomaty"}, {"s": "net-elektrichestva-v-kvartire", "t": "Нет света в квартире: причины и что делать в 2026 году", "i": "🔍", "c": "poisk-neispravnostej"}, {"s": "ne-rabotayut-rozetki-v-odnoj-komnate", "t": "Не работают розетки в одной комнате: причины и решения", "i": "🔍", "c": "poisk-neispravnostej"}, {"s": "net-napryazheniya-v-rozetke-a-avtomat-vklyuchen-prichiny", "t": "Нет напряжения в розетке, а автомат включен: 7 причин и что делать", "i": "🔍", "c": "poisk-neispravnostej"}, {"s": "neispravnosti-avtomaticheskogo-vyklyuchatelya", "t": "Неисправности автоматического выключателя: причины и решения", "i": "🛡️", "c": "elektroshchit-i-avtomaty"}, {"s": "neobkhodimye-instrumenty-dlya-elektrika", "t": "Инструменты для электрика: полный список 2026 года с ценами", "i": "🔧", "c": "instrumenty-i-zamery"}, {"s": "ne-vklyuchaetsya-avtomat-v-shchitke-posle-vyklyucheniya-chto-delat", "t": "Автомат не включается после выключения — причины и решения", "i": "🔍", "c": "poisk-neispravnostej"}, {"s": "ne-rabotaet-rozetka-v-kvartire-no-napryazhenie-est", "t": "Розетка не работает, а напряжение есть: причины и решения", "i": "🔍", "c": "poisk-neispravnostej"}, {"s": "ne-rabotayut-rozetki-na-kukhne", "t": "Не работают розетки на кухне: причины и что делать в 2026 году", "i": "🍳", "c": "elektrika-na-kukhne"}, {"s": "ne-vzvoditsya-avtomat-v-shchitke", "t": "Не взводится автомат в щитке: 7 причин и что делать в 2026 году", "i": "🛡️", "c": "elektroshchit-i-avtomaty"}, {"s": "ne-zavoditsya-benzogenerator-posle-goda-prostoya", "t": "Бензогенератор не заводится после года простоя: 10 причин и ремонт", "i": "🏡", "c": "chastnyj-dom-i-dacha"}, {"s": "ne-zavoditsya-generator-benzinovyj-posle-dolgogo-prostoya-prichiny", "t": "Не заводится бензогенератор после простоя: 7 причин и решения", "i": "🔍", "c": "poisk-neispravnostej"}, {"s": "neispravnosti-rozetki-elektricheskoj", "t": "Неисправности розетки: 7 признаков поломки и способы ремонта", "i": "🔌", "c": "rozetki-i-vyklyuchateli"}, {"s": "ne-vklyuchaetsya-vvodnoj-avtomat", "t": "Не включается вводной автомат: причины и решения (2026)", "i": "🛡️", "c": "elektroshchit-i-avtomaty"}, {"s": "ne-zavoditsya-generator-benzinovyj-posle-dolgogo-prostoya", "t": "Не заводится бензогенератор после простоя: 7 причин и решения", "i": "🏡", "c": "chastnyj-dom-i-dacha"}, {"s": "net-elektrichestva-v-rozetkakh-a-svet-est", "t": "Нет электричества в розетках, а свет есть: причины и решение", "i": "🔍", "c": "poisk-neispravnostej"}, {"s": "net-sveta-v-kvartire-chto-delat", "t": "Нет света в квартире: что делать — пошаговая инструкция 2026", "i": "🔍", "c": "poisk-neispravnostej"}, {"s": "ne-vklyuchaetsya-rubilnik-v-elektroshchitke-chto-delat", "t": "Не включается рубильник в щитке: причины и решение", "i": "📁", "c": null}, {"s": "ne-rabotaet-chast-rozetok-v-kvartire-chto-delat", "t": "Не работает часть розеток в квартире: причины и решение", "i": "🔍", "c": "poisk-neispravnostej"}, {"s": "nepreryvnaya-rabota-benzogeneratora", "t": "Непрерывная работа бензогенератора: ресурс, перегрев и обслуживание", "i": "🔋", "c": "stabilizatory-i-ibp"}, {"s": "neispravnost-avtomata-v-shchitke-kak-opredelit", "t": "Неисправность автомата в щитке: как определить и устранить", "i": "🛡️", "c": "elektroshchit-i-avtomaty"}, {"s": "net-zazemleniya-v-rozetke", "t": "Нет заземления в розетке: что делать и чем опасно", "i": "⚠️", "c": "bezopasnost-i-zazemlenie"}, {"s": "net-napryazheniya-v-rozetke-chto-delat", "t": "Нет напряжения в розетке: пошаговый план действий", "i": "🔍", "c": "poisk-neispravnostej"}, {"s": "ne-khvataet-rozetok-v-komnate", "t": "Не хватает розеток в комнате: 7 решений без штробления", "i": "🔌", "c": "rozetki-i-vyklyuchateli"}, {"s": "net-nulya-v-rozetke-chto-delat", "t": "Нет нуля в розетке: причины, поиск обрыва и методы ремонта", "i": "🔍", "c": "poisk-neispravnostej"}, {"s": "ne-zavoditsya-invertornyj-generator-benzinovyj-prichina", "t": "Не заводится бензиновый инверторный генератор: причины и ремонт", "i": "🔍", "c": "poisk-neispravnostej"}, {"s": "neotklyuchaemaya-liniya-v-elektroshchite", "t": "Неотключаемая линия в щите: схема, назначение и монтаж", "i": "🛡️", "c": "elektroshchit-i-avtomaty"}, {"s": "ne-rabotayut-rozetki-v-kvartire-a-svet-est-chto-delat", "t": "Не работают розетки в квартире, а свет есть: причины и ремонт", "i": "🔍", "c": "poisk-neispravnostej"}, {"s": "net-zazemleniya-v-kvartire-kak-byt", "t": "Нет заземления в квартире: что делать и как обезопасить", "i": "⚠️", "c": "bezopasnost-i-zazemlenie"}, {"s": "ne-derzhitsya-rozetka-v-podrozetnike-chto-delat", "t": "Не держится розетка в подрозетнике: как починить и закрепить", "i": "🔌", "c": "rozetki-i-vyklyuchateli"}, {"s": "ne-rabotayut-rozetki-na-kukhne-a-svet-est", "t": "Не работают розетки на кухне, а свет есть: поиск неисправности", "i": "🔍", "c": "poisk-neispravnostej"}, {"s": "ne-vklyuchaetsya-svet-v-kvartire-avtomaty-vklyucheny", "t": "Не включается свет в квартире: автоматы включены — поиск неисправности", "i": "🔍", "c": "poisk-neispravnostej"}, {"s": "ne-rabotayut-rozetki-v-odnoj-komnate-a-svet-est-chto-delat", "t": "Не работают розетки в одной комнате, а свет есть: причины и решение", "i": "🔍", "c": "poisk-neispravnostej"}, {"s": "negoryuchaya-gofra-dlya-elektroprovodki-v-derevyannom-dome", "t": "Негорючая гофра для проводки в деревянном доме: выбор и монтаж", "i": "🧵", "c": "provodka-i-kabeli"}, {"s": "neispravna-rozetka-kak-pishetsya", "t": "Неисправна розетка: как пишется и что делать? | Полный гайд", "i": "🔍", "c": "poisk-neispravnostej"}, {"s": "nesushchaya-zhila-sip-eto", "t": "Несущая жила СИП: функции, сечение и устройство", "i": "🧵", "c": "provodka-i-kabeli"}, {"s": "neispravnost-uzo-priznaki", "t": "Неисправность УЗО: признаки, причины и поиск поломки", "i": "🔍", "c": "poisk-neispravnostej"}, {"s": "ne-vklyuchaetsya-avtomat-v-shchitke-posle-vyklyucheniya", "t": "Не включается автомат в щитке: причины и способы устранения", "i": "🛡️", "c": "elektroshchit-i-avtomaty"}]